cardiac_shared/__init__.py
cardiac_shared/batch/__init__.py
cardiac_shared/cache/__init__.py
cardiac_shared/config/__init__.py
cardiac_shared/data/__init__.py
cardiac_shared/data/batch_discovery.py
cardiac_shared/data/batch_manager.py
cardiac_shared/data/datasets.py
cardiac_shared/data/paired_dataset.py
cardiac_shared/data/registry.py
cardiac_shared/data_sources/__init__.py
cardiac_shared/data_sources/manager.py
cardiac_shared/environment/__init__.py
cardiac_shared/environment/runtime_detector.py
cardiac_shared/hardware/__init__.py
cardiac_shared/hardware/cpu_optimizer.py
cardiac_shared/hardware/detector.py
cardiac_shared/hardware/gpu_utils.py
cardiac_shared/hardware/optimizer.py
cardiac_shared/hardware/profiles.py
cardiac_shared/io/__init__.py
cardiac_shared/io/dicom.py
cardiac_shared/io/nifti.py
cardiac_shared/io/preloader.py
cardiac_shared/io/zip_handler.py
cardiac_shared/parallel/__init__.py
cardiac_shared/parallel/processor.py
cardiac_shared/preprocessing/__init__.py
cardiac_shared/preprocessing/dicom_converter.py
cardiac_shared/preprocessing/pipeline.py
cardiac_shared/preprocessing/thickness.py
cardiac_shared/progress/__init__.py
cardiac_shared/progress/tracker.py
cardiac_shared/tissue/__init__.py
cardiac_shared/tissue/classifier.py
cardiac_shared/utils/__init__.py
cardiac_shared/vertebra/__init__.py
cardiac_shared/vertebra/detector.py
cardiac_shared-0.9.1.dist-info/licenses/LICENSE
cardiac_shared-0.9.1.dist-info/METADATA
cardiac_shared-0.9.1.dist-info/WHEEL
cardiac_shared-0.9.1.dist-info/top_level.txt
cardiac_shared-0.9.1.dist-info/RECORD
