Metadata-Version: 2.4
Name: cardiac-shared
Version: 0.9.1
Summary: Shared utilities for cardiac imaging analysis - batch management, preprocessing pipelines, hardware detection, IO, data sources, vertebra detection, tissue classification, dataset registry, thickness detection, paired dataset management
Author-email: Rong Zhu <zhurong0525@gmail.com>
Maintainer-email: Rong Zhu <zhurong0525@gmail.com>
License: MIT
Project-URL: Homepage, https://github.com/zhurong2020/cardiac-shared
Project-URL: Documentation, https://github.com/zhurong2020/cardiac-shared/blob/main/README.md
Project-URL: Repository, https://github.com/zhurong2020/cardiac-shared
Project-URL: Bug Tracker, https://github.com/zhurong2020/cardiac-shared/issues
Project-URL: Changelog, https://github.com/zhurong2020/cardiac-shared/blob/main/CHANGELOG.md
Keywords: cardiac,medical-imaging,dicom,nifti,ct-scan,hardware-detection,gpu,totalsegmentator
Classifier: Development Status :: 3 - Alpha
Classifier: Intended Audience :: Science/Research
Classifier: Intended Audience :: Healthcare Industry
Classifier: License :: OSI Approved :: MIT License
Classifier: Operating System :: OS Independent
Classifier: Programming Language :: Python :: 3
Classifier: Programming Language :: Python :: 3.8
Classifier: Programming Language :: Python :: 3.9
Classifier: Programming Language :: Python :: 3.10
Classifier: Programming Language :: Python :: 3.11
Classifier: Programming Language :: Python :: 3.12
Classifier: Topic :: Scientific/Engineering :: Medical Science Apps.
Requires-Python: >=3.8
License-File: LICENSE
Requires-Dist: numpy<2.0,>=1.19.0
Requires-Dist: psutil>=5.8.0
Requires-Dist: pyyaml>=5.3.0
Provides-Extra: dicom
Requires-Dist: pydicom>=2.0.0; extra == "dicom"
Provides-Extra: nifti
Requires-Dist: nibabel>=3.2.0; extra == "nifti"
Provides-Extra: gpu
Requires-Dist: torch>=1.9.0; extra == "gpu"
Provides-Extra: all
Requires-Dist: pydicom>=2.0.0; extra == "all"
Requires-Dist: nibabel>=3.2.0; extra == "all"
Requires-Dist: torch>=1.9.0; extra == "all"
Provides-Extra: dev
Requires-Dist: pytest>=7.0.0; extra == "dev"
Requires-Dist: pytest-cov>=4.0.0; extra == "dev"
Requires-Dist: black>=22.0.0; extra == "dev"
Requires-Dist: ruff>=0.1.0; extra == "dev"
Dynamic: license-file
